<Properties StartupConfiguration="{1E4D6630-E355-4F28-96C2-EA682586FF1B}|Default">
  <MonoDevelop.Ide.Workbench>
    <Pads>
      <Pad Id="ProjectPad">
        <State name="__root__">
          <Node name="DatingApp.API" expanded="True">
            <Node name="DatingApp.API" expanded="True">
              <Node name="Dependencies" expanded="True">
                <Node name="FrameworkReferences" expanded="True" />
              </Node>
              <Node name="Data" expanded="True" />
              <Node name="Migrations" expanded="True" />
              <Node name="Models" expanded="True" selected="True" />
            </Node>
          </Node>
        </State>
      </Pad>
    </Pads>
  </MonoDevelop.Ide.Workbench>
  <MonoDevelop.Ide.ItemProperties.DatingApp.API PreferredExecutionTarget="/Applications/Google Chrome.app" />
  <MonoDevelop.Ide.DebuggingService.PinnedWatches />
  <MonoDevelop.Ide.Workspace ActiveConfiguration="Debug" />
  <MonoDevelop.Ide.DebuggingService.Breakpoints>
    <BreakpointStore />
  </MonoDevelop.Ide.DebuggingService.Breakpoints>
  <MultiItemStartupConfigurations />
</Properties>